{
  "title": "2026 日本旅遊趨勢: 在地美食攻略",
  "slug": "2026-japan-food-guide",
  "primary_keyword": "日本美食攻略",
  "secondary_keywords": [
    "2026日本旅遊",
    "日本必吃",
    "日本餐廳預約",
    "tablecheck教學",
    "日本在地美食"
  ],
  "page_type": "Cluster Page",
  "search_intent": "Informational",
  "target_audience": "計劃於 2026 年前往日本旅遊，希望體驗深度在地飲食文化，但對日語不通且擔心預約困難的 25-45 歲自由行旅客。",
  "tone": "專業且具同理心 (Professional, Empathetic)。理解旅客想吃好料但怕踩雷或訂不到位的焦慮，提供具體、可操作的建議，語氣如同一位熟門熟路的在地嚮導。",
  "category": "海外旅遊",
  "word_count_target": 2200,
  "search_intent_research": {
    "query": "日本美食攻略 2026 趨勢",
    "top_results_summary": [
      {
        "title": "2025-2026 日本必吃十大美食清單",
        "hook_style": "清單式開場，直接列舉食物種類",
        "h2_count": 10
      },
      {
        "title": "日本旅遊餐飲費用大漲？如何省錢吃美食",
        "hook_style": "痛點開場，強調價格上漲",
        "h2_count": 5
      }
    ],
    "recommended_hook_strategy": "以「旅遊型態轉變」為 Hook：引用 2025 年後的觀光數據，指出「Walk-in (隨意進店)」的時代已結束，2026 年的美食關鍵字是「預約制」與「體驗式餐飲」，若不提前規劃將只能吃便利商店。",
    "content_gaps": [
      "大多數競品只介紹「吃什麼」，未介紹「如何成功預約」(Tabelog/TableCheck 操作)",
      "缺乏針對 2026 年「現金 vs 電子支付」在鄉下小店的最新實況分析",
      "未提及針對外國旅客的「飲食禁忌」與「特殊飲食」(素食/無麩質) 的最新友善程度"
    ]
  },
  "outline": [
    {
      "section": "Introduction",
      "h2_title": "引言：2026 日本美食之旅，為何不再能「說走就走」？",
      "key_points": [
        "具體 Hook：根據日本觀光廳預測，2026 入境遊客將創新高，熱門餐廳「完全預約制」比例已突破 70%。",
        "痛點陳述：許多旅客到了現場才發現名店大排長龍或拒絕現場客，導致行程大亂。",
        "文章預覽：本文不只列出必吃清單，更將傳授 3 大預約神器使用法、在地人推薦的隱藏版美食區域，以及 2026 最新用餐禮儀。"
      ]
    },
    {
      "section": "Main Body",
      "h2_title": "趨勢解讀：2026 日本餐飲界的 3 大變化",
      "key_points": [
        "變化一：價格與品質的兩極化（高價位 Omakase vs 平價立食文化的復興）。",
        "變化二：數位化點餐與支付的全面普及（即使是拉麵店也開始用 QR Code 點餐）。",
        "變化三：永續食材與「地產地消」成為新顯學（介紹 Gibier 野味料理或有機農家餐廳的興起）。"
      ]
    },
    {
      "section": "Main Body",
      "h2_title": "攻略教學：搞定日本餐廳預約的實戰指南",
      "key_points": [
        "工具推薦：詳細比較 Tabelog (看評分)、TableCheck (免日語預約)、AutoReserve (AI 代訂) 的優缺點。",
        "實作步驟：以 TableCheck 為例，Step-by-step 教學如何綁卡訂位與處理取消條款。",
        "備案策略：如果真的訂不到位，百貨公司地下街 (Depachika) 與超市半價時段是最佳救星。"
      ]
    },
    {
      "section": "Main Body",
      "h2_title": "在地推薦：除了東京大阪，老饕轉向這些「美食藍海」",
      "key_points": [
        "福岡 (Fukuoka)：屋台文化的新規定與推薦路線（避開觀光客陷阱）。",
        "名古屋 (Nagoya)：獨特的「早餐文化 (Morning Service)」體驗升級。",
        "北陸地區 (金澤/富山)：隨著新幹線延伸，成為 2026 海鮮愛好者的新聖地（強調比築地/豐洲更具 CP 值）。"
      ]
    },
    {
      "section": "Main Body",
      "h2_title": "避雷指南：2026 旅客常犯的餐飲錯誤",
      "key_points": [
        "No-show 的嚴重性：解釋日本店家對無故缺席的嚴格懲罰（可能導致信用卡被扣全額）。",
        "香水與著裝：在高檔壽司店或懷石料理店的具體禮儀規範。",
        "多人分食 (Share) 的禁忌：說明「一人一品」的基本規矩，避免店家困擾。"
      ]
    },
    {
      "section": "Conclusion",
      "h2_title": "結語：用舌尖記憶日本，從尊重在地文化開始",
      "key_points": [
        "重點摘要：預約是關鍵、工具要善用、禮儀要遵守。",
        "價值昇華：真正的美食攻略不只是吃得好，更是透過飲食與當地建立連結。",
        "CTA：準備好出發了嗎？立即查看我們的「東京」與「沖繩」景點懶人包，規劃您的完美行程。"
      ]
    }
  ],
  "cta": "想知道更多日本旅遊省錢撇步？歡迎訂閱 FunIT 電子報，或參考下方的日本上網 SIM 卡評比，確保您在找餐廳時網路不卡關！",
  "internal_link_opportunities": [],
  "external_reference_suggestions": [
    "Tabelog (日本最大美食評鑑網站)",
    "TableCheck (多語言預約平台)",
    "日本觀光廳 (JNTO) 官方飲食指南"
  ],
  "forbidden_terms": [
    "CP值爆表 (過於聳動)",
    "絕對好吃 (口味主觀)",
    "必去 (改用「高度推薦」)",
    "最頂級 (除非有獎項佐證)"
  ],
  "brand_terms": [
    "FunIT 旅遊小幫手",
    "智慧旅遊",
    "在地體驗"
  ],
  "image_strategy": "使用高畫質、暖色調的食物特寫，搭配「預約介面截圖」作為教學輔助，避免使用過度修圖的網美照，強調真實感。",
  "h2_structure": "Introduction -> 趨勢解讀 -> 攻略教學 (預約) -> 在地推薦 (地區) -> 避雷指南 -> Conclusion",
  "existing_content_raw": ""
}